LICENSE.txt
MANIFEST.in
README.rst
setup.cfg
setup.py
dtw_c/__init__.py
dtw_c/dtw_c.c
dtw_c/dtw_c.pyx
dtw_c.egg-info/PKG-INFO
dtw_c.egg-info/SOURCES.txt
dtw_c.egg-info/dependency_links.txt
dtw_c.egg-info/requires.txt
dtw_c.egg-info/top_level.txt
src/dtw_sub_c.c
src/dtw_sub_c.h