Metadata-Version: 2.1
Name: dtw-c
Version: 1.0.2
Summary: Dynamic Time Warping (DTW) implementation in C for Python
Home-page: https://github.com/patrickltobing/dtw_c
Author: Patrick Lumban Tobing
Author-email: patrickltobing@gmail.com
License: UNKNOWN
Keywords: dynamic time warping,dtw
Platform: UNKNOWN
Provides-Extra: sdist
Provides-Extra: test
